experiment_collection/__init__.py
experiment_collection/collection_abc.py
experiment_collection/collection_remote.py
experiment_collection/experiment.py
experiment_collection/utils.py
experiment_collection_core/__init__.py
experiment_collection_core/service_pb2.py
experiment_collection_core/service_pb2_grpc.py
experiment_collection-0.2.7.dist-info/LICENSE
experiment_collection-0.2.7.dist-info/METADATA
experiment_collection-0.2.7.dist-info/WHEEL
experiment_collection-0.2.7.dist-info/entry_points.txt
experiment_collection-0.2.7.dist-info/top_level.txt
experiment_collection-0.2.7.dist-info/RECORD
