Metadata-Version: 2.1
Name: experiment-collection
Version: 0.2.7
Summary: Experiment collection
Home-page: https://github.com/AsciiShell/experiment_collection
Author: AsciiShell (Aleksey Podchezertsev)
Author-email: dev@asciishell.ru
License: MIT
Keywords: python3
Platform: UNKNOWN
Classifier: Intended Audience :: Developers
Classifier: Programming Language :: Python :: 3
Classifier: Programming Language :: Python :: 3.6
Classifier: Programming Language :: Python :: 3.7
Classifier: Programming Language :: Python :: 3.8
Classifier: License :: OSI Approved :: MIT License
Classifier: Operating System :: POSIX
Classifier: Operating System :: POSIX :: Linux
Requires-Python: >=3.6
Requires-Dist: grpcio (>=1.8.6)
Requires-Dist: protobuf (>=3.0.0)
Requires-Dist: pandas (>=1.0.0)
